pyCardDeck/__init__.py
pyCardDeck/cards.py
pyCardDeck/deck.py
pyCardDeck/errors.py
pyCardDeck/standard_deck.yml
pyCardDeck-1.4.0.dist-info/LICENSE
pyCardDeck-1.4.0.dist-info/METADATA
pyCardDeck-1.4.0.dist-info/WHEEL
pyCardDeck-1.4.0.dist-info/top_level.txt
pyCardDeck-1.4.0.dist-info/RECORD
