Metadata-Version: 2.1
Name: pyCardDeck
Version: 1.4.0
Summary: Logic for decks with cards
Home-page: https://www.djetelina.cz/project/pycarddeck/
Author: David Jetelina
Author-email: david@djetelina.cz
License: MIT
Keywords: cards deck card game shuffle draw discard
Platform: UNKNOWN
Classifier: Development Status :: 5 - Production/Stable
Classifier: Intended Audience :: Developers
Classifier: Topic :: Software Development :: Libraries
Classifier: Topic :: Software Development :: Libraries :: Python Modules
Classifier: Topic :: Games/Entertainment
Classifier: Topic :: Utilities
Classifier: License :: OSI Approved :: MIT License
Classifier: Natural Language :: English
Classifier: Operating System :: OS Independent
Classifier: Programming Language :: Python
Classifier: Programming Language :: Python :: 3 :: Only
Classifier: Programming Language :: Python :: 3.3
Classifier: Programming Language :: Python :: 3.4
Classifier: Programming Language :: Python :: 3.5
Classifier: Programming Language :: Python :: 3.6
Classifier: Programming Language :: Python :: Implementation :: PyPy
Requires-Dist: PyYAML (>=3.11)
Requires-Dist: jsonpickle (>=0.9.3)
